gitlab_operations/__init__.py
gitlab_operations/deleteissue.py
gitlab_operations/gitinstance.py
gitlab_operations/userconfig.py
gitlab_issue_delete-1.1.3.dist-info/LICENSE
gitlab_issue_delete-1.1.3.dist-info/METADATA
gitlab_issue_delete-1.1.3.dist-info/WHEEL
gitlab_issue_delete-1.1.3.dist-info/entry_points.txt
gitlab_issue_delete-1.1.3.dist-info/top_level.txt
gitlab_issue_delete-1.1.3.dist-info/RECORD
